pygst/__init__.py
pygst/pygst.py
pygst-0.0.4.dist-info/METADATA
pygst-0.0.4.dist-info/WHEEL
pygst-0.0.4.dist-info/top_level.txt
pygst-0.0.4.dist-info/RECORD
