Metadata-Version: 2.1
Name: pygst
Version: 0.0.4
Summary: Python global stock time
Home-page: https://github.com/taobun/pygst
Author: Bun Uthaitirat
License: UNKNOWN
Platform: UNKNOWN
Classifier: Programming Language :: Python :: 3
Classifier: License :: OSI Approved :: MIT License
Classifier: Operating System :: OS Independent
Requires-Python: >=3.6
Requires-Dist: pytz
